Metadata-Version: 2.1
Name: sengine-cli
Version: 1.4.9
Summary: S-Egnine CLI is a command line interface for the Sonic Engine extensions manager.
Home-page: UNKNOWN
Author: Soufiane Oualil, Ahmed Bargady
License: UNKNOWN
Platform: UNKNOWN
